setup.py
email/iterators.py
email/message.py
micropython_email.message.egg-info/PKG-INFO
micropython_email.message.egg-info/SOURCES.txt
micropython_email.message.egg-info/dependency_links.txt
micropython_email.message.egg-info/requires.txt
micropython_email.message.egg-info/top_level.txt